ymery/__init__.py
ymery/__main__.py
ymery/app.py
ymery/data_bag.py
ymery/decorators.py
ymery/dispatcher.py
ymery/lang.py
ymery/logging.py
ymery/plugin_manager.py
ymery/result.py
ymery/stringcase.py
ymery/types.py
ymery/utils.py
ymery/backend/audio_buffer.py
ymery/backend/types.py
ymery/editor/layouts/app.yaml
ymery/editor/layouts/data.yaml
ymery/editor/layouts/menu.yaml
ymery/editor/layouts/widgets.yaml
ymery/frontend/composite.py
ymery/frontend/types.py
ymery/frontend/widget.py
ymery/frontend/widget_factory.py
ymery/frontend/layouts/builtin.yaml
ymery/plugins/__init__.py
ymery/plugins/backend/data_tree/main.py
ymery/plugins/backend/filesystem/main.py
ymery/plugins/backend/kernel/main.py
ymery/plugins/backend/log_tree/main.py
ymery/plugins/backend/simple_data_tree/main.py
ymery/plugins/backend/soundfile/main.py
ymery/plugins/backend/waveform/main.py
ymery/plugins/backend/waveform_st/main.py
ymery/plugins/frontend/cool_bar/main.py
ymery/plugins/frontend/drag/main.py
ymery/plugins/frontend/editing/main.py
ymery/plugins/frontend/hello_imgui_main_window/main.py
ymery/plugins/frontend/imgui_main_window/main.py
ymery/plugins/frontend/imguizmo/main.py
ymery/plugins/frontend/immvision/main.py
ymery/plugins/frontend/implot/main.py
ymery/plugins/frontend/implot3d/main.py
ymery/plugins/frontend/knobs/main.py
ymery/plugins/frontend/listbox/main.py
ymery/plugins/frontend/markdown/main.py
ymery/plugins/frontend/matplotlib/main.py
ymery/plugins/frontend/nanovg/main.py
ymery/plugins/frontend/node_editor/main.py
ymery/plugins/frontend/popup/main.py
ymery/plugins/frontend/selectable/main.py
ymery/plugins/frontend/simple/main.py
ymery/plugins/frontend/spinner/main.py
ymery/plugins/frontend/table/main.py
ymery/plugins/frontend/text_editor/main.py
ymery/plugins/frontend/toggle/main.py
ymery/plugins/frontend/tree_like/main.py
ymery/demo/classic/app.yaml
ymery/demo/classic/data.yaml
ymery/demo/classic/demo.yaml
ymery/demo/classic/foreach-key-demo.yaml
ymery/demo/classic/implot-demo.yaml
ymery-0.0.76.dist-info/METADATA
ymery-0.0.76.dist-info/WHEEL
ymery-0.0.76.dist-info/entry_points.txt
ymery-0.0.76.dist-info/licenses/LICENSE
ymery-0.0.76.dist-info/RECORD
